{"version":1,"config":{"env":{"MONGO_URI":"mongodb://localhost:27017/tndfctrust","SIGNING_TOKEN":"158AC701-C10C-4603-B693-F255A112F6DC","USERS":[{"email":"santhoshlfms@gmail.com","password":"12345678","displayName":"Santhosh Nelson","emailVerified":true,"disabled":false},{"email":"muru@gmail.com","password":"12345678","displayName":"Muru S","emailVerified":true,"disabled":false}]},"webpack":null,"webpackDevMiddleware":null,"eslint":{"ignoreDuringBuilds":false},"typescript":{"ignoreBuildErrors":false},"distDir":"build","cleanDistDir":true,"assetPrefix":"","configOrigin":"next.config.js","useFileSystemPublicRoutes":true,"generateEtags":true,"pageExtensions":["tsx","ts","jsx","js"],"target":"server","poweredByHeader":true,"compress":false,"analyticsId":"","images":{"deviceSizes":[640,750,828,1080,1200,1920,2048,3840],"imageSizes":[16,32,48,64,96,128,256,384],"path":"/_next/image","loader":"default","domains":[],"disableStaticImages":false,"minimumCacheTTL":60},"devIndicators":{"buildActivity":true},"onDemandEntries":{"maxInactiveAge":60000,"pagesBufferLength":2},"amp":{"canonicalBase":""},"basePath":"","sassOptions":{},"trailingSlash":false,"i18n":{"locales":["en-US"],"defaultLocale":"en-US"},"productionBrowserSourceMaps":false,"optimizeFonts":true,"excludeDefaultMomentLocales":true,"serverRuntimeConfig":{},"publicRuntimeConfig":{"firebaseApp":{"apiKey":"AIzaSyA8gem19RNVjjfKIK1t6U5x1mf7N8KLJNM","authDomain":"tdfct-7491d.firebaseapp.com","databaseURL":"https://tdfct-7491d-default-rtdb.firebaseio.com","projectId":"tdfct-7491d","storageBucket":"tdfct-7491d.appspot.com","messagingSenderId":"913117926204","appId":"1:913117926204:web:24a021bb1f029d56e0c439"},"firebaseEmulators":{"auth":{"port":33007},"database":{"port":33008},"firestore":{"port":33009},"pubsub":{"port":33010},"storage":{"port":33011},"ui":{"enabled":true,"port":33012}}},"reactStrictMode":true,"httpAgentOptions":{"keepAlive":true},"experimental":{"swcLoader":false,"swcMinify":false,"cpus":15,"sharedPool":false,"plugins":false,"profiling":false,"isrFlushToDisk":true,"workerThreads":false,"pageEnv":false,"optimizeImages":false,"optimizeCss":false,"scrollRestoration":false,"stats":false,"externalDir":false,"reactRoot":false,"disableOptimizedLoading":false,"gzipSize":true,"craCompat":false,"esmExternals":false,"staticPageGenerationTimeout":60,"isrMemoryCacheSize":52428800,"nftTracing":false,"concurrentFeatures":false},"future":{"strictPostcssConfiguration":false}},"appDir":"/Users/sannelson/Documents/js/js-hack/tndfctrust-api","files":["build/routes-manifest.json","build/server/pages-manifest.json","build/build-manifest.json","build/prerender-manifest.json","build/react-loadable-manifest.json","build/server/font-manifest.json","build/BUILD_ID"],"ignore":["node_modules/next/dist/compiled/@ampproject/toolbox-optimizer/**/*"]}